nlppreprocess/__init__.py
nlppreprocess/list.py
nlppreprocess/nlppreprocess.py
nlppreprocess-0.1.1.dist-info/LICENSE
nlppreprocess-0.1.1.dist-info/METADATA
nlppreprocess-0.1.1.dist-info/WHEEL
nlppreprocess-0.1.1.dist-info/top_level.txt
nlppreprocess-0.1.1.dist-info/RECORD
