Metadata-Version: 2.1
Name: nlppreprocess
Version: 0.1.1
Summary: This package contains preprocessing functions
Home-page: https://github.com/gaganmanku96/nlppreprocess
Author: Gagandeep Singh
Author-email: gaganmanku96@gmail.com
License: License :: OSI Approved :: MIT License
Platform: UNKNOWN
Classifier: Programming Language :: Python
Classifier: Programming Language :: Python :: 3
Classifier: Operating System :: OS Independent
Requires-Python: >=3.4
